README.md
setup.py
Yaplee.egg-info/PKG-INFO
Yaplee.egg-info/SOURCES.txt
Yaplee.egg-info/dependency_links.txt
Yaplee.egg-info/entry_points.txt
Yaplee.egg-info/not-zip-safe
Yaplee.egg-info/requires.txt
Yaplee.egg-info/top_level.txt
yaplee/__init__.py
yaplee/app_manager.py
yaplee/core.py
yaplee/defaults.py
yaplee/main.py
yaplee/server.py
yaplee/template.py
yaplee/app/__init__.py
yaplee/app/Blank/__init__.py
yaplee/app/Blank/config.py
yaplee/app/Blank/controller.py
yaplee/app/Blank/static/__init__.py
yaplee/app/Blank/template/__init__.py
yaplee/app/HelloWorld/__init__.py
yaplee/app/HelloWorld/application.py
yaplee/app/HelloWorld/config.py
yaplee/app/HelloWorld/pages/__init__.py
yaplee/app/HelloWorld/pages/HelloWorld/__init__.py
yaplee/app/HelloWorld/pages/HelloWorld/config.py
yaplee/app/HelloWorld/pages/HelloWorld/controller.py
yaplee/app/HelloWorld/pages/HelloWorld/static/__init__.py
yaplee/app/HelloWorld/pages/HelloWorld/template/__init__.py
yaplee/utils/__init__.py