Metadata-Version: 2.1
Name: Yaplee
Version: 0.0.8
Summary: Yaplee is a fun and simple python framework to build user interfaces on web pages
Home-page: https://github.com/YapleeProject
Author: Matin Najafi
Author-email: matinnajafi.dev@gmail.com
License: MIT
Platform: UNKNOWN
Classifier: License :: OSI Approved :: MIT License
Classifier: Programming Language :: Python :: 3.6
Classifier: Programming Language :: Python :: 3.7
Classifier: Programming Language :: Python :: 3.8
Requires-Python: >=3.6
